
{
  "ebooks": [
    {
      "id": "P3NoEQAAQBAJ",
      "title": "🌿 La Charte des Relations Sacrées de la Nouvelle Terre",
      "subtitle": "",
      "format": "eBook",
      "contributors": "Guillaume Lessard",
      "publisher": "iD01t Productions",
      "language": "en",
      "date": "2024-01-01",
      "cover_hd": "https://books.google.com/books/content?id=P3NoEQAAQBAJ&printsec=frontcover&img=1&zoom=3&source=gbs_api",
      "buy": "https://play.google.com/store/books/details?id=P3NoEQAAQBAJ",
      "price": "9.99"
    }
  ],
  "audiobooks": []
}
